scrapscii/.data/sections.txt
scrapscii/__init__.py
scrapscii/data.py
scrapscii/items.py
scrapscii/middlewares.py
scrapscii/pipelines.py
scrapscii/settings.py
scrapscii/spiders/__init__.py
scrapscii/spiders/asciiart_spider.py
scrapscii/spiders/twitchquotes_spider.py
scrapscii/unicode.py
scrapscii-0.0.5.dist-info/METADATA
scrapscii-0.0.5.dist-info/WHEEL
scrapscii-0.0.5.dist-info/RECORD
